tradernet_cli/__init__.py
tradernet_cli/__main__.py
tradernet_cli/tradernet_client.py
tradernet_cli/commands/__init__.py
tradernet_cli/commands/get_broker_report.py
tradernet_cli/commands/get_my_position.py
tradernet_cli-1.0.5.dist-info/LICENSE
tradernet_cli-1.0.5.dist-info/METADATA
tradernet_cli-1.0.5.dist-info/WHEEL
tradernet_cli-1.0.5.dist-info/top_level.txt
tradernet_cli-1.0.5.dist-info/RECORD
