Metadata-Version: 2.1
Name: tradernet-cli
Version: 1.0.5
Summary: A small TraderNet API (https://tradernet.com/) client for automation purposes.
Home-page: https://github.com/VolodymyrKuksa/tradernet_cli
Author: Volodymyr Kuksa
Author-email: volodymyrkuksa@gmail.com
License: UNKNOWN
Platform: UNKNOWN
Classifier: Programming Language :: Python :: 3
Classifier: License :: OSI Approved :: MIT License
Classifier: Operating System :: OS Independent
Requires-Python: >=3.7
Requires-Dist: requests
